{"name":"build-javascript","namedChunkGroups":{"app":{"name":"app","assets":[{"name":"webpack-runtime-99e172f25ca7dcb0be2a.js","size":3646},{"name":"framework-70a9f4e36460b584a9c5.js","size":140353},{"name":"styles.f31d2b58efbd68ee6691.css","size":9605},{"name":"app-017a2a9f7e77bb900768.js","size":69582}],"filteredAssets":0,"assetsSize":223186,"filteredAuxiliaryAssets":7,"auxiliaryAssetsSize":696242},"component---src-pages-404-js":{"name":"component---src-pages-404-js","assets":[{"name":"component---src-pages-404-js-5314946dc74ffc8eab0f.js","size":4455}],"filteredAssets":0,"assetsSize":4455,"filteredAuxiliaryAssets":1,"auxiliaryAssetsSize":10513},"component---src-pages-index-js":{"name":"component---src-pages-index-js","assets":[{"name":"component---src-pages-index-js-c0aec596a1106a0f44c4.js","size":4840}],"filteredAssets":0,"assetsSize":4840,"filteredAuxiliaryAssets":1,"auxiliaryAssetsSize":11843},"component---src-templates-blog-post-js":{"name":"component---src-templates-blog-post-js","assets":[{"name":"component---src-templates-blog-post-js-01bea7ae608fffb48c50.js","size":5310}],"filteredAssets":0,"assetsSize":5310,"filteredAuxiliaryAssets":1,"auxiliaryAssetsSize":13348}},"assetsByChunkName":{"app":["webpack-runtime-99e172f25ca7dcb0be2a.js","framework-70a9f4e36460b584a9c5.js","styles.f31d2b58efbd68ee6691.css","app-017a2a9f7e77bb900768.js"],"component---src-pages-404-js":["component---src-pages-404-js-5314946dc74ffc8eab0f.js"],"component---src-pages-index-js":["component---src-pages-index-js-c0aec596a1106a0f44c4.js"],"component---src-templates-blog-post-js":["component---src-templates-blog-post-js-01bea7ae608fffb48c50.js"]},"childAssetsByChunkName":{}}